{"symbol": "BLTE", "historical": [{"date": "2025-12-18", "open": 154.8, "high": 162, "low": 153, "close": 154.54, "adjClose": 154.54, "volume": 261000, "unadjustedVolume": 261000, "change": -0.26, "changePercent": -0.16796, "vwap": 156.085, "label": "December 18, 25", "changeOverTime": -0.0016796}, {"date": "2025-12-17", "open": 149.5, "high": 157.5, "low": 149.46, "close": 154.21, "adjClose": 154.21, "volume": 287100, "unadjustedVolume": 287100, "change": 4.71, "changePercent": 3.15, "vwap": 152.6675, "label": "December 17, 25", "changeOverTime": 0.0315}, {"date": "2025-12-16", "open": 141.14, "high": 149.27, "low": 141, "close": 149.13, "adjClose": 149.13, "volume": 144328, "unadjustedVolume": 144328, "change": 7.99, "changePercent": 5.66, "vwap": 145.135, "label": "December 16, 25", "changeOverTime": 0.0566}, {"date": "2025-12-15", "open": 142.5, "high": 147.08, "low": 141.57, "close": 142.53, "adjClose": 142.53, "volume": 124848, "unadjustedVolume": 124848, "change": 0.03, "changePercent": 0.02105263, "vwap": 143.42, "label": "December 15, 25", "changeOverTime": 0.0002105263}, {"date": "2025-12-12", "open": 150.25, "high": 151.16, "low": 140.99, "close": 141.32, "adjClose": 141.32, "volume": 170000, "unadjustedVolume": 170000, "change": -8.93, "changePercent": -5.94, "vwap": 145.93, "label": "December 12, 25", "changeOverTime": -0.0594}, {"date": "2025-12-11", "open": 149.04, "high": 161.32, "low": 144.88, "close": 150.24, "adjClose": 150.24, "volume": 555200, "unadjustedVolume": 555200, "change": 1.2, "changePercent": 0.80515, "vwap": 151.37, "label": "December 11, 25", "changeOverTime": 0.0080515}, {"date": "2025-12-10", "open": 148.33, "high": 148.65, "low": 145.01, "close": 146.99, "adjClose": 146.99, "volume": 207885, "unadjustedVolume": 207885, "change": -1.34, "changePercent": -0.90339, "vwap": 147.245, "label": "December 10, 25", "changeOverTime": -0.0090339}, {"date": "2025-12-09", "open": 149.3, "high": 151.6, "low": 147.01, "close": 149.13, "adjClose": 149.13, "volume": 246500, "unadjustedVolume": 246500, "change": -0.17, "changePercent": -0.11386, "vwap": 149.26, "label": "December 09, 25", "changeOverTime": -0.0011386}, {"date": "2025-12-08", "open": 148, "high": 154, "low": 146.61, "close": 149.91, "adjClose": 149.91, "volume": 125800, "unadjustedVolume": 125800, "change": 1.91, "changePercent": 1.29, "vwap": 149.63, "label": "December 08, 25", "changeOverTime": 0.0129}, {"date": "2025-12-05", "open": 151, "high": 151.79, "low": 140.07, "close": 150, "adjClose": 150, "volume": 314500, "unadjustedVolume": 314500, "change": -1, "changePercent": -0.66225, "vwap": 148.215, "label": "December 05, 25", "changeOverTime": -0.0066225}, {"date": "2025-12-04", "open": 152, "high": 152.5, "low": 143.71, "close": 151.27, "adjClose": 151.27, "volume": 388086, "unadjustedVolume": 388086, "change": -0.73, "changePercent": -0.48026, "vwap": 149.87, "label": "December 04, 25", "changeOverTime": -0.0048026}, {"date": "2025-12-03", "open": 153.96, "high": 155.5, "low": 151, "close": 151.79, "adjClose": 151.79, "volume": 189535, "unadjustedVolume": 189535, "change": -2.17, "changePercent": -1.41, "vwap": 153.0625, "label": "December 03, 25", "changeOverTime": -0.0141}, {"date": "2025-12-02", "open": 160.43, "high": 160.55, "low": 145.69, "close": 150.84, "adjClose": 150.84, "volume": 1038771, "unadjustedVolume": 1038771, "change": -9.59, "changePercent": -5.98, "vwap": 154.3775, "label": "December 02, 25", "changeOverTime": -0.0598}, {"date": "2025-12-01", "open": 153.5, "high": 154.99, "low": 130.06, "close": 154.02, "adjClose": 154.02, "volume": 753209, "unadjustedVolume": 753209, "change": 0.52, "changePercent": 0.33876, "vwap": 148.1425, "label": "December 01, 25", "changeOverTime": 0.0033876}, {"date": "2025-11-28", "open": 130, "high": 138.1, "low": 129, "close": 137.44, "adjClose": 137.44, "volume": 75300, "unadjustedVolume": 75300, "change": 7.44, "changePercent": 5.72, "vwap": 133.635, "label": "November 28, 25", "changeOverTime": 0.0572}]}