{"symbol": "SE", "historical": [{"date": "2025-05-29", "open": 166, "high": 166.81, "low": 160.38, "close": 161.21, "adjClose": 161.21, "volume": 4288826, "unadjustedVolume": 4288826, "change": -4.79, "changePercent": -2.89, "vwap": 163.6, "label": "May 29, 25", "changeOverTime": -0.0289}, {"date": "2025-05-28", "open": 166.79, "high": 167.65, "low": 164.2, "close": 164.92, "adjClose": 164.92, "volume": 4782547, "unadjustedVolume": 4782547, "change": -1.87, "changePercent": -1.12, "vwap": 165.89, "label": "May 28, 25", "changeOverTime": -0.0112}, {"date": "2025-05-27", "open": 166, "high": 169.28, "low": 164.51, "close": 165.24, "adjClose": 165.24, "volume": 6394244, "unadjustedVolume": 6394244, "change": -0.76, "changePercent": -0.45783, "vwap": 166.2575, "label": "May 27, 25", "changeOverTime": -0.0045783}, {"date": "2025-05-23", "open": 159.33, "high": 165.9, "low": 157.3, "close": 164.06, "adjClose": 164.06, "volume": 3656800, "unadjustedVolume": 3656800, "change": 4.73, "changePercent": 2.97, "vwap": 161.6475, "label": "May 23, 25", "changeOverTime": 0.0297}, {"date": "2025-05-22", "open": 161.1, "high": 162.74, "low": 160.31, "close": 160.69, "adjClose": 160.69, "volume": 3033300, "unadjustedVolume": 3033300, "change": -0.41, "changePercent": -0.2545, "vwap": 161.21, "label": "May 22, 25", "changeOverTime": -0.002545}, {"date": "2025-05-21", "open": 162.61, "high": 164.99, "low": 161.68, "close": 163.26, "adjClose": 163.26, "volume": 2849200, "unadjustedVolume": 2849200, "change": 0.65, "changePercent": 0.39973, "vwap": 163.135, "label": "May 21, 25", "changeOverTime": 0.0039973}, {"date": "2025-05-20", "open": 163.2, "high": 163.6, "low": 161.02, "close": 162.41, "adjClose": 162.41, "volume": 2319709, "unadjustedVolume": 2319709, "change": -0.79, "changePercent": -0.48407, "vwap": 162.5575, "label": "May 20, 25", "changeOverTime": -0.0048407}, {"date": "2025-05-19", "open": 160, "high": 162.98, "low": 158, "close": 162.72, "adjClose": 162.72, "volume": 3972226, "unadjustedVolume": 3972226, "change": 2.72, "changePercent": 1.7, "vwap": 160.925, "label": "May 19, 25", "changeOverTime": 0.017}, {"date": "2025-05-16", "open": 165, "high": 165.31, "low": 161.28, "close": 161.51, "adjClose": 161.51, "volume": 3701100, "unadjustedVolume": 3701100, "change": -3.49, "changePercent": -2.12, "vwap": 163.275, "label": "May 16, 25", "changeOverTime": -0.0212}, {"date": "2025-05-15", "open": 162, "high": 164.71, "low": 160.45, "close": 164.63, "adjClose": 164.63, "volume": 6286300, "unadjustedVolume": 6286300, "change": 2.63, "changePercent": 1.62, "vwap": 162.9475, "label": "May 15, 25", "changeOverTime": 0.0162}, {"date": "2025-05-14", "open": 158.88, "high": 163.26, "low": 156.59, "close": 163.18, "adjClose": 163.18, "volume": 11197944, "unadjustedVolume": 11197944, "change": 4.3, "changePercent": 2.71, "vwap": 160.4775, "label": "May 14, 25", "changeOverTime": 0.0271}, {"date": "2025-05-13", "open": 152.01, "high": 155.52, "low": 147.26, "close": 154.13, "adjClose": 154.13, "volume": 12348426, "unadjustedVolume": 12348426, "change": 2.12, "changePercent": 1.39, "vwap": 152.23, "label": "May 13, 25", "changeOverTime": 0.0139}, {"date": "2025-05-12", "open": 143.02, "high": 143.98, "low": 139.12, "close": 142.45, "adjClose": 142.45, "volume": 7194400, "unadjustedVolume": 7194400, "change": -0.57, "changePercent": -0.39855, "vwap": 142.1425, "label": "May 12, 25", "changeOverTime": -0.0039855}, {"date": "2025-05-09", "open": 142.19, "high": 143.26, "low": 138.24, "close": 139.17, "adjClose": 139.17, "volume": 4692100, "unadjustedVolume": 4692100, "change": -3.02, "changePercent": -2.12, "vwap": 140.715, "label": "May 09, 25", "changeOverTime": -0.0212}]}