{"symbol": "SYM", "historical": [{"date": "2025-07-03", "open": 42.89, "high": 47.98, "low": 42.52, "close": 47.91, "adjClose": 47.91, "volume": 4967000, "unadjustedVolume": 4967000, "change": 5.02, "changePercent": 11.7, "vwap": 45.325, "label": "July 03, 25", "changeOverTime": 0.117}, {"date": "2025-07-02", "open": 39.66, "high": 42.79, "low": 38.88, "close": 42.2, "adjClose": 42.2, "volume": 3222700, "unadjustedVolume": 3222700, "change": 2.54, "changePercent": 6.4, "vwap": 40.8825, "label": "July 02, 25", "changeOverTime": 0.064}, {"date": "2025-07-01", "open": 38.51, "high": 40.84, "low": 38.19, "close": 39.68, "adjClose": 39.68, "volume": 2427543, "unadjustedVolume": 2427543, "change": 1.17, "changePercent": 3.04, "vwap": 39.305, "label": "July 01, 25", "changeOverTime": 0.0304}, {"date": "2025-06-30", "open": 37.66, "high": 39.5, "low": 37.45, "close": 38.85, "adjClose": 38.85, "volume": 2470424, "unadjustedVolume": 2470424, "change": 1.19, "changePercent": 3.16, "vwap": 38.365, "label": "June 30, 25", "changeOverTime": 0.0316}, {"date": "2025-06-27", "open": 37.2, "high": 38.08, "low": 36.4, "close": 37.25, "adjClose": 37.25, "volume": 1649600, "unadjustedVolume": 1649600, "change": 0.05, "changePercent": 0.13441, "vwap": 37.2325, "label": "June 27, 25", "changeOverTime": 0.0013441}, {"date": "2025-06-26", "open": 35.55, "high": 37.25, "low": 34.98, "close": 37.16, "adjClose": 37.16, "volume": 2721900, "unadjustedVolume": 2721900, "change": 1.61, "changePercent": 4.53, "vwap": 36.235, "label": "June 26, 25", "changeOverTime": 0.0453}, {"date": "2025-06-25", "open": 33.23, "high": 35.65, "low": 32.88, "close": 34.91, "adjClose": 34.91, "volume": 2737532, "unadjustedVolume": 2737532, "change": 1.68, "changePercent": 5.06, "vwap": 34.1675, "label": "June 25, 25", "changeOverTime": 0.0506}, {"date": "2025-06-24", "open": 33.49, "high": 34, "low": 32.09, "close": 32.2, "adjClose": 32.2, "volume": 2702900, "unadjustedVolume": 2702900, "change": -1.29, "changePercent": -3.85, "vwap": 32.945, "label": "June 24, 25", "changeOverTime": -0.0385}, {"date": "2025-06-23", "open": 33.89, "high": 34.07, "low": 32.07, "close": 32.89, "adjClose": 32.89, "volume": 1968228, "unadjustedVolume": 1968228, "change": -1, "changePercent": -2.95, "vwap": 33.23, "label": "June 23, 25", "changeOverTime": -0.0295}, {"date": "2025-06-20", "open": 37, "high": 37.8, "low": 33.5, "close": 34, "adjClose": 34, "volume": 4462740, "unadjustedVolume": 4462740, "change": -3, "changePercent": -8.11, "vwap": 35.575, "label": "June 20, 25", "changeOverTime": -0.0811}, {"date": "2025-06-18", "open": 31.2, "high": 38.19, "low": 30.7, "close": 35.7, "adjClose": 35.7, "volume": 7562033, "unadjustedVolume": 7562033, "change": 4.5, "changePercent": 14.42, "vwap": 33.9475, "label": "June 18, 25", "changeOverTime": 0.1442}, {"date": "2025-06-17", "open": 32.37, "high": 32.74, "low": 31.14, "close": 31.16, "adjClose": 31.16, "volume": 1875432, "unadjustedVolume": 1875432, "change": -1.21, "changePercent": -3.74, "vwap": 31.8525, "label": "June 17, 25", "changeOverTime": -0.0374}, {"date": "2025-06-16", "open": 28.95, "high": 32.54, "low": 28.49, "close": 32.45, "adjClose": 32.45, "volume": 4055809, "unadjustedVolume": 4055809, "change": 3.5, "changePercent": 12.09, "vwap": 30.6075, "label": "June 16, 25", "changeOverTime": 0.1209}, {"date": "2025-06-13", "open": 27.3, "high": 28.35, "low": 27.26, "close": 27.97, "adjClose": 27.97, "volume": 1134700, "unadjustedVolume": 1134700, "change": 0.67, "changePercent": 2.45, "vwap": 27.72, "label": "June 13, 25", "changeOverTime": 0.0245}]}