{"symbol": "BMA", "historical": [{"date": "2026-01-16", "open": 90, "high": 94.15, "low": 90, "close": 92.67, "adjClose": 92.67, "volume": 261646, "unadjustedVolume": 261646, "change": 2.67, "changePercent": 2.97, "vwap": 91.705, "label": "January 16, 26", "changeOverTime": 0.0297}, {"date": "2026-01-15", "open": 91, "high": 93.36, "low": 88.05, "close": 90.08, "adjClose": 90.08, "volume": 277142, "unadjustedVolume": 277142, "change": -0.92, "changePercent": -1.01, "vwap": 90.6225, "label": "January 15, 26", "changeOverTime": -0.0101}, {"date": "2026-01-14", "open": 93.36, "high": 94.46, "low": 89.75, "close": 90.97, "adjClose": 90.97, "volume": 385200, "unadjustedVolume": 385200, "change": -2.39, "changePercent": -2.56, "vwap": 92.135, "label": "January 14, 26", "changeOverTime": -0.0256}, {"date": "2026-01-13", "open": 93.89, "high": 94.93, "low": 92.9, "close": 93.3, "adjClose": 93.3, "volume": 223000, "unadjustedVolume": 223000, "change": -0.59, "changePercent": -0.62839, "vwap": 93.755, "label": "January 13, 26", "changeOverTime": -0.0062839}, {"date": "2026-01-12", "open": 94.59, "high": 96.93, "low": 93.3, "close": 94.66, "adjClose": 94.66, "volume": 173400, "unadjustedVolume": 173400, "change": 0.07, "changePercent": 0.07400359, "vwap": 94.87, "label": "January 12, 26", "changeOverTime": 0.0007400359}, {"date": "2026-01-09", "open": 94.86, "high": 96.5, "low": 94.08, "close": 95.45, "adjClose": 95.45, "volume": 306500, "unadjustedVolume": 306500, "change": 0.59, "changePercent": 0.62197, "vwap": 95.2225, "label": "January 09, 26", "changeOverTime": 0.0062197}, {"date": "2026-01-08", "open": 90.98, "high": 96.8, "low": 89.19, "close": 95.31, "adjClose": 95.31, "volume": 340000, "unadjustedVolume": 340000, "change": 4.33, "changePercent": 4.76, "vwap": 93.07, "label": "January 08, 26", "changeOverTime": 0.0476}, {"date": "2026-01-07", "open": 89.99, "high": 93.01, "low": 87.37, "close": 90.9, "adjClose": 90.9, "volume": 429700, "unadjustedVolume": 429700, "change": 0.91, "changePercent": 1.01, "vwap": 90.3175, "label": "January 07, 26", "changeOverTime": 0.0101}, {"date": "2026-01-06", "open": 92.69, "high": 95.73, "low": 89.11, "close": 89.52, "adjClose": 89.52, "volume": 358664, "unadjustedVolume": 358664, "change": -3.17, "changePercent": -3.42, "vwap": 91.7625, "label": "January 06, 26", "changeOverTime": -0.0342}, {"date": "2026-01-05", "open": 89.28, "high": 93.19, "low": 88.88, "close": 92.5, "adjClose": 92.5, "volume": 291347, "unadjustedVolume": 291347, "change": 3.22, "changePercent": 3.61, "vwap": 90.9625, "label": "January 05, 26", "changeOverTime": 0.0361}, {"date": "2026-01-02", "open": 90.76, "high": 91.29, "low": 86.44, "close": 88.77, "adjClose": 88.77, "volume": 178443, "unadjustedVolume": 178443, "change": -1.99, "changePercent": -2.19, "vwap": 89.315, "label": "January 02, 26", "changeOverTime": -0.0219}, {"date": "2025-12-31", "open": 89.68, "high": 90.92, "low": 88.46, "close": 90.16, "adjClose": 90.16, "volume": 127737, "unadjustedVolume": 127737, "change": 0.48, "changePercent": 0.53524, "vwap": 89.805, "label": "December 31, 25", "changeOverTime": 0.0053524}, {"date": "2025-12-30", "open": 90.01, "high": 91.4, "low": 89.49, "close": 89.79, "adjClose": 89.79, "volume": 177120, "unadjustedVolume": 177120, "change": -0.22, "changePercent": -0.24442, "vwap": 90.1725, "label": "December 30, 25", "changeOverTime": -0.0024442}, {"date": "2025-12-29", "open": 91.3, "high": 93.49, "low": 90.25, "close": 90.33, "adjClose": 90.33, "volume": 329427, "unadjustedVolume": 329427, "change": -0.97, "changePercent": -1.06, "vwap": 91.3425, "label": "December 29, 25", "changeOverTime": -0.0106}]}