{"symbol": "EBR", "historical": [{"date": "2025-11-07", "open": 10.73, "high": 11.05, "low": 10.71, "close": 11.03, "adjClose": 10.7, "volume": 2185448, "unadjustedVolume": 2185448, "change": 0.3, "changePercent": 2.8, "vwap": 10.88, "label": "November 07, 25", "changeOverTime": 0.028}, {"date": "2025-11-06", "open": 11.24, "high": 11.27, "low": 10.9, "close": 10.92, "adjClose": 10.59, "volume": 2616100, "unadjustedVolume": 2616100, "change": -0.32, "changePercent": -2.85, "vwap": 11.0825, "label": "November 06, 25", "changeOverTime": -0.0285}]}