{"symbol": "TSEM", "historical": [{"date": "2025-12-04", "open": 114.19, "high": 115.46, "low": 110.14, "close": 115.07, "adjClose": 115.07, "volume": 1615100, "unadjustedVolume": 1615100, "change": 0.88, "changePercent": 0.77065, "vwap": 113.715, "label": "December 04, 25", "changeOverTime": 0.0077065}, {"date": "2025-12-03", "open": 114.68, "high": 116.13, "low": 109.81, "close": 116.01, "adjClose": 116.01, "volume": 1812947, "unadjustedVolume": 1812947, "change": 1.33, "changePercent": 1.16, "vwap": 114.1575, "label": "December 03, 25", "changeOverTime": 0.0116}, {"date": "2025-12-02", "open": 114.21, "high": 119.82, "low": 114.12, "close": 116.46, "adjClose": 116.46, "volume": 3907100, "unadjustedVolume": 3907100, "change": 2.25, "changePercent": 1.97, "vwap": 116.1525, "label": "December 02, 25", "changeOverTime": 0.0197}, {"date": "2025-12-01", "open": 108.15, "high": 112.1, "low": 107.84, "close": 111.86, "adjClose": 111.86, "volume": 1983700, "unadjustedVolume": 1983700, "change": 3.71, "changePercent": 3.43, "vwap": 109.9875, "label": "December 01, 25", "changeOverTime": 0.0343}, {"date": "2025-11-28", "open": 105.4, "high": 109.06, "low": 105.2, "close": 108.11, "adjClose": 108.11, "volume": 1936300, "unadjustedVolume": 1936300, "change": 2.71, "changePercent": 2.57, "vwap": 106.9425, "label": "November 28, 25", "changeOverTime": 0.0257}, {"date": "2025-11-26", "open": 100.74, "high": 106.04, "low": 100.08, "close": 103.46, "adjClose": 103.46, "volume": 2444924, "unadjustedVolume": 2444924, "change": 2.72, "changePercent": 2.7, "vwap": 102.58, "label": "November 26, 25", "changeOverTime": 0.027}, {"date": "2025-11-25", "open": 94.4, "high": 98.84, "low": 92.95, "close": 98, "adjClose": 98, "volume": 1238524, "unadjustedVolume": 1238524, "change": 3.61, "changePercent": 3.81, "vwap": 96.0475, "label": "November 25, 25", "changeOverTime": 0.0381}, {"date": "2025-11-24", "open": 95.12, "high": 97.42, "low": 94.34, "close": 96.05, "adjClose": 96.05, "volume": 1226121, "unadjustedVolume": 1226121, "change": 0.93, "changePercent": 0.97771, "vwap": 95.7325, "label": "November 24, 25", "changeOverTime": 0.0097771}, {"date": "2025-11-21", "open": 91.61, "high": 93.99, "low": 87.3, "close": 93.65, "adjClose": 93.65, "volume": 1899595, "unadjustedVolume": 1899595, "change": 2.04, "changePercent": 2.23, "vwap": 91.6375, "label": "November 21, 25", "changeOverTime": 0.0223}, {"date": "2025-11-20", "open": 102.99, "high": 103.62, "low": 91.01, "close": 91.61, "adjClose": 91.61, "volume": 2104433, "unadjustedVolume": 2104433, "change": -11.38, "changePercent": -11.05, "vwap": 97.3075, "label": "November 20, 25", "changeOverTime": -0.1105}, {"date": "2025-11-19", "open": 96.52, "high": 100.4, "low": 96.26, "close": 98.53, "adjClose": 98.53, "volume": 1195216, "unadjustedVolume": 1195216, "change": 2.01, "changePercent": 2.08, "vwap": 97.9275, "label": "November 19, 25", "changeOverTime": 0.0208}, {"date": "2025-11-18", "open": 95.43, "high": 98.74, "low": 94.1, "close": 96.67, "adjClose": 96.67, "volume": 1369284, "unadjustedVolume": 1369284, "change": 1.24, "changePercent": 1.3, "vwap": 96.235, "label": "November 18, 25", "changeOverTime": 0.013}, {"date": "2025-11-17", "open": 99.02, "high": 100.75, "low": 94.25, "close": 95.37, "adjClose": 95.37, "volume": 1527637, "unadjustedVolume": 1527637, "change": -3.65, "changePercent": -3.69, "vwap": 97.3475, "label": "November 17, 25", "changeOverTime": -0.0369}, {"date": "2025-11-14", "open": 94.92, "high": 101.15, "low": 94, "close": 99.26, "adjClose": 99.26, "volume": 1713073, "unadjustedVolume": 1713073, "change": 4.34, "changePercent": 4.57, "vwap": 97.3325, "label": "November 14, 25", "changeOverTime": 0.0457}]}