{"symbol": "JOBY", "historical": [{"date": "2023-09-27", "open": 6.29, "high": 6.565, "low": 6.27, "close": 6.47, "adjClose": 6.47, "volume": 6288552, "unadjustedVolume": 6288600, "change": 0.18, "changePercent": 2.86, "vwap": 6.46, "label": "September 27, 23", "changeOverTime": 0.0286}, {"date": "2023-09-26", "open": 6.33, "high": 6.555, "low": 6.16, "close": 6.21, "adjClose": 6.21, "volume": 7364842, "unadjustedVolume": 7364800, "change": -0.12, "changePercent": -1.9, "vwap": 6.29, "label": "September 26, 23", "changeOverTime": -0.019}, {"date": "2023-09-25", "open": 6.5, "high": 6.83, "low": 6.35, "close": 6.48, "adjClose": 6.48, "volume": 13567076, "unadjustedVolume": 13567100, "change": -0.02, "changePercent": -0.30769, "vwap": 6.57, "label": "September 25, 23", "changeOverTime": -0.0030769}, {"date": "2023-09-22", "open": 6.38, "high": 6.49, "low": 6.175, "close": 6.22, "adjClose": 6.22, "volume": 4331294, "unadjustedVolume": 4327800, "change": -0.16, "changePercent": -2.51, "vwap": 6.29, "label": "September 22, 23", "changeOverTime": -0.0251}, {"date": "2023-09-21", "open": 6.41, "high": 6.495, "low": 6.22, "close": 6.26, "adjClose": 6.26, "volume": 4984861, "unadjustedVolume": 4974700, "change": -0.15, "changePercent": -2.34, "vwap": 6.34, "label": "September 21, 23", "changeOverTime": -0.0234}, {"date": "2023-09-20", "open": 6.83, "high": 6.9682, "low": 6.59, "close": 6.62, "adjClose": 6.62, "volume": 3020005, "unadjustedVolume": 3020000, "change": -0.21, "changePercent": -3.07, "vwap": 6.73, "label": "September 20, 23", "changeOverTime": -0.0307}, {"date": "2023-09-19", "open": 6.69, "high": 6.88, "low": 6.61, "close": 6.77, "adjClose": 6.77, "volume": 4860199, "unadjustedVolume": 4851100, "change": 0.08, "changePercent": 1.2, "vwap": 6.74, "label": "September 19, 23", "changeOverTime": 0.012}, {"date": "2023-09-18", "open": 6.72, "high": 7.05, "low": 6.55, "close": 6.83, "adjClose": 6.83, "volume": 10071300, "unadjustedVolume": 10071300, "change": 0.11, "changePercent": 1.64, "vwap": 6.85, "label": "September 18, 23", "changeOverTime": 0.0164}, {"date": "2023-09-15", "open": 6.85, "high": 6.915, "low": 6.45, "close": 6.54, "adjClose": 6.54, "volume": 12290300, "unadjustedVolume": 12268300, "change": -0.31, "changePercent": -4.53, "vwap": 6.56, "label": "September 15, 23", "changeOverTime": -0.0453}, {"date": "2023-09-14", "open": 6.9, "high": 7, "low": 6.78, "close": 6.94, "adjClose": 6.94, "volume": 4972062, "unadjustedVolume": 4972100, "change": 0.04, "changePercent": 0.57971, "vwap": 6.91, "label": "September 14, 23", "changeOverTime": 0.0057971}, {"date": "2023-09-13", "open": 6.96, "high": 7.045, "low": 6.87, "close": 6.88, "adjClose": 6.88, "volume": 4684693, "unadjustedVolume": 4684700, "change": -0.08, "changePercent": -1.15, "vwap": 6.92, "label": "September 13, 23", "changeOverTime": -0.0115}, {"date": "2023-09-12", "open": 7.2, "high": 7.31, "low": 6.98, "close": 6.99, "adjClose": 6.99, "volume": 3565644, "unadjustedVolume": 3565600, "change": -0.21, "changePercent": -2.92, "vwap": 7.11, "label": "September 12, 23", "changeOverTime": -0.0292}, {"date": "2023-09-11", "open": 7.39, "high": 7.47, "low": 7.27, "close": 7.28, "adjClose": 7.28, "volume": 3526606, "unadjustedVolume": 3526600, "change": -0.11, "changePercent": -1.49, "vwap": 7.35, "label": "September 11, 23", "changeOverTime": -0.0149}, {"date": "2023-09-08", "open": 7.25, "high": 7.355, "low": 7.19, "close": 7.3, "adjClose": 7.3, "volume": 2969145, "unadjustedVolume": 2966300, "change": 0.05, "changePercent": 0.68966, "vwap": 7.28, "label": "September 08, 23", "changeOverTime": 0.0068966}, {"date": "2023-09-07", "open": 7.17, "high": 7.37, "low": 7.01, "close": 7.25, "adjClose": 7.25, "volume": 3142623, "unadjustedVolume": 3142600, "change": 0.08, "changePercent": 1.12, "vwap": 7.22, "label": "September 07, 23", "changeOverTime": 0.0112}]}