{"symbol": "MRK", "historical": [{"date": "2026-01-08", "open": 110.61, "high": 112.9, "low": 109.25, "close": 110.99, "adjClose": 110.99, "volume": 20278830, "unadjustedVolume": 20278830, "change": 0.38, "changePercent": 0.34355, "vwap": 110.9375, "label": "January 08, 26", "changeOverTime": 0.0034355}, {"date": "2026-01-07", "open": 109.51, "high": 111.46, "low": 107.95, "close": 108.6, "adjClose": 108.6, "volume": 16322345, "unadjustedVolume": 16322345, "change": -0.905, "changePercent": -0.83097, "vwap": 109.38, "label": "January 07, 26", "changeOverTime": -0.0083097}, {"date": "2026-01-06", "open": 107.68, "high": 110.17, "low": 107.68, "close": 108.87, "adjClose": 108.87, "volume": 14479000, "unadjustedVolume": 14479000, "change": 1.19, "changePercent": 1.11, "vwap": 108.6, "label": "January 06, 26", "changeOverTime": 0.0111}, {"date": "2026-01-05", "open": 107.01, "high": 108.44, "low": 105.8, "close": 107.44, "adjClose": 107.44, "volume": 15863319, "unadjustedVolume": 15863319, "change": 0.43, "changePercent": 0.40183, "vwap": 107.1725, "label": "January 05, 26", "changeOverTime": 0.0040183}, {"date": "2026-01-02", "open": 105.53, "high": 106.62, "low": 104.43, "close": 106.45, "adjClose": 106.45, "volume": 9992435, "unadjustedVolume": 9992435, "change": 0.92, "changePercent": 0.87179, "vwap": 105.7575, "label": "January 02, 26", "changeOverTime": 0.0087179}, {"date": "2025-12-31", "open": 105.94, "high": 106.1, "low": 104.99, "close": 105.26, "adjClose": 105.26, "volume": 7557325, "unadjustedVolume": 7557325, "change": -0.675, "changePercent": -0.64187, "vwap": 105.5725, "label": "December 31, 25", "changeOverTime": -0.0064187}, {"date": "2025-12-30", "open": 106.73, "high": 106.88, "low": 105.64, "close": 106.06, "adjClose": 106.06, "volume": 6498303, "unadjustedVolume": 6498303, "change": -0.67, "changePercent": -0.62775, "vwap": 106.3275, "label": "December 30, 25", "changeOverTime": -0.0062775}, {"date": "2025-12-29", "open": 106.85, "high": 107.59, "low": 106.43, "close": 106.62, "adjClose": 106.62, "volume": 8086900, "unadjustedVolume": 8086900, "change": -0.23, "changePercent": -0.21526, "vwap": 106.8725, "label": "December 29, 25", "changeOverTime": -0.0021526}, {"date": "2025-12-26", "open": 106.45, "high": 107.05, "low": 106.03, "close": 106.78, "adjClose": 106.78, "volume": 6280701, "unadjustedVolume": 6280701, "change": 0.33, "changePercent": 0.31, "vwap": 106.5775, "label": "December 26, 25", "changeOverTime": 0.0031}, {"date": "2025-12-24", "open": 105.37, "high": 106.95, "low": 105.28, "close": 106.45, "adjClose": 106.45, "volume": 5335048, "unadjustedVolume": 5335048, "change": 1.09, "changePercent": 1.02, "vwap": 106.0125, "label": "December 24, 25", "changeOverTime": 0.0102}, {"date": "2025-12-23", "open": 104.56, "high": 105.39, "low": 104.33, "close": 105.04, "adjClose": 105.04, "volume": 13587500, "unadjustedVolume": 13587500, "change": 0.48, "changePercent": 0.45907, "vwap": 104.83, "label": "December 23, 25", "changeOverTime": 0.0045907}, {"date": "2025-12-22", "open": 100.63, "high": 104.95, "low": 100.4, "close": 104.72, "adjClose": 104.72, "volume": 17136247, "unadjustedVolume": 17136247, "change": 4.09, "changePercent": 4.06, "vwap": 102.675, "label": "December 22, 25", "changeOverTime": 0.0406}, {"date": "2025-12-19", "open": 100.6, "high": 102.2, "low": 100.11, "close": 101.09, "adjClose": 101.09, "volume": 44980247, "unadjustedVolume": 44980247, "change": 0.49, "changePercent": 0.48708, "vwap": 101, "label": "December 19, 25", "changeOverTime": 0.0048708}]}