{"symbol": "CDNS", "historical": [{"date": "2025-11-04", "open": 330.06, "high": 336.06, "low": 325.59, "close": 333.22, "adjClose": 333.22, "volume": 3048000, "unadjustedVolume": 3048000, "change": 3.16, "changePercent": 0.9574, "vwap": 331.2325, "label": "November 04, 25", "changeOverTime": 0.009574}, {"date": "2025-11-03", "open": 341.71, "high": 341.71, "low": 331, "close": 335.41, "adjClose": 335.41, "volume": 1469100, "unadjustedVolume": 1469100, "change": -6.29, "changePercent": -1.84, "vwap": 337.4575, "label": "November 03, 25", "changeOverTime": -0.0184}, {"date": "2025-10-31", "open": 338.73, "high": 340.73, "low": 336.22, "close": 338.69, "adjClose": 338.69, "volume": 1429974, "unadjustedVolume": 1429974, "change": -0.04, "changePercent": -0.01180882, "vwap": 338.5925, "label": "October 31, 25", "changeOverTime": -0.0001180882}, {"date": "2025-10-30", "open": 340, "high": 342.2, "low": 333.41, "close": 336.09, "adjClose": 336.09, "volume": 1559514, "unadjustedVolume": 1559514, "change": -3.91, "changePercent": -1.15, "vwap": 337.925, "label": "October 30, 25", "changeOverTime": -0.0115}, {"date": "2025-10-29", "open": 337.3, "high": 347, "low": 334, "close": 341.43, "adjClose": 341.43, "volume": 2413024, "unadjustedVolume": 2413024, "change": 4.13, "changePercent": 1.22, "vwap": 339.9325, "label": "October 29, 25", "changeOverTime": 0.0122}, {"date": "2025-10-28", "open": 339.01, "high": 348.08, "low": 327.17, "close": 341.3, "adjClose": 341.3, "volume": 3216000, "unadjustedVolume": 3216000, "change": 2.29, "changePercent": 0.6755, "vwap": 338.89, "label": "October 28, 25", "changeOverTime": 0.006755}, {"date": "2025-10-27", "open": 357.53, "high": 357.53, "low": 346, "close": 351.4, "adjClose": 351.4, "volume": 4236538, "unadjustedVolume": 4236538, "change": -6.12, "changePercent": -1.71, "vwap": 353.115, "label": "October 27, 25", "changeOverTime": -0.0171}, {"date": "2025-10-24", "open": 339.76, "high": 351.13, "low": 339.76, "close": 345.1, "adjClose": 345.1, "volume": 1856400, "unadjustedVolume": 1856400, "change": 5.34, "changePercent": 1.57, "vwap": 343.9375, "label": "October 24, 25", "changeOverTime": 0.0157}, {"date": "2025-10-23", "open": 329.3, "high": 338.18, "low": 327.62, "close": 337.27, "adjClose": 337.27, "volume": 1533700, "unadjustedVolume": 1533700, "change": 7.97, "changePercent": 2.42, "vwap": 333.0925, "label": "October 23, 25", "changeOverTime": 0.0242}, {"date": "2025-10-22", "open": 333.44, "high": 336.5, "low": 326.16, "close": 330.51, "adjClose": 330.51, "volume": 1996692, "unadjustedVolume": 1996692, "change": -2.93, "changePercent": -0.87872, "vwap": 331.6525, "label": "October 22, 25", "changeOverTime": -0.0087872}, {"date": "2025-10-21", "open": 327.53, "high": 335.12, "low": 327.11, "close": 333.45, "adjClose": 333.45, "volume": 1258822, "unadjustedVolume": 1258822, "change": 5.92, "changePercent": 1.81, "vwap": 330.8025, "label": "October 21, 25", "changeOverTime": 0.0181}, {"date": "2025-10-20", "open": 327.79, "high": 331.12, "low": 326.39, "close": 329.64, "adjClose": 329.64, "volume": 1458433, "unadjustedVolume": 1458433, "change": 1.85, "changePercent": 0.56439, "vwap": 328.735, "label": "October 20, 25", "changeOverTime": 0.0056439}, {"date": "2025-10-17", "open": 322.59, "high": 328.21, "low": 320, "close": 326.12, "adjClose": 326.12, "volume": 1481818, "unadjustedVolume": 1481818, "change": 3.53, "changePercent": 1.09, "vwap": 324.23, "label": "October 17, 25", "changeOverTime": 0.0109}, {"date": "2025-10-16", "open": 326.18, "high": 327.05, "low": 320.08, "close": 324.25, "adjClose": 324.25, "volume": 1788568, "unadjustedVolume": 1788568, "change": -1.93, "changePercent": -0.5917, "vwap": 324.39, "label": "October 16, 25", "changeOverTime": -0.005917}, {"date": "2025-10-15", "open": 330.65, "high": 330.65, "low": 321.39, "close": 324.1, "adjClose": 324.1, "volume": 1599600, "unadjustedVolume": 1599600, "change": -6.55, "changePercent": -1.98, "vwap": 326.6975, "label": "October 15, 25", "changeOverTime": -0.0198}]}