[{"symbol": "GRAB", "price": 4.38, "beta": 0.901, "volAvg": 49297637, "mktCap": 17366700000, "lastDiv": 0, "range": "3.36-6.62", "changes": -0.01, "companyName": "Grab Holdings Limited", "currency": "USD", "cik": "0001855612", "isin": "KYG4124C1096", "cusip": "G4124C109", "exchange": "NASDAQ Global Select", "exchangeShortName": "NASDAQ", "industry": "Software - Application", "website": "https://www.grab.com/sg", "description": "Grab Holdings Limited provides superapps that allows access to mobility, delivery, financial services, and enterprise offerings through its mobile application in Cambodia, Indonesia, Malaysia, Myanmar, the Philippines, Singapore, Thailand, and Vietnam. The company is headquartered in Singapore.", "ceo": "Ping Yeow Tan", "sector": "Technology", "country": "SG", "fullTimeEmployees": "11267", "phone": "65 8557 397864", "address": "3 Media Close", "city": "Singapore", "state": null, "zip": "138498", "dcfDiff": 6.99557, "dcf": -3.495572540791874, "image": "https://images.financialmodelingprep.com/symbol/GRAB.png", "ipoDate": "2020-12-01", "defaultImage": false, "isEtf": false, "isActivelyTrading": true, "isAdr": false, "isFund": false}]